guancodes/GrayCode.py
guancodes/GuanCodeGenerator.py
guancodes/__init__.py
guancodes-0.0.3.dist-info/LICENSE.md
guancodes-0.0.3.dist-info/METADATA
guancodes-0.0.3.dist-info/WHEEL
guancodes-0.0.3.dist-info/top_level.txt
guancodes-0.0.3.dist-info/RECORD
