Metadata-Version: 2.1
Name: guancodes
Version: 0.0.3
Summary: Package for generating Guan Codes
Author: Tomasz Rybotycki
Author-email: rybotycki.tomasz+guancodes@gmail.com
License: Apache License 2.0.
Platform: UNKNOWN
Classifier: Intended Audience :: Developers
Classifier: License :: OSI Approved :: Apache Software License
Classifier: Natural Language :: English
License-File: LICENSE.md
Requires-Dist: requests
Requires-Dist: importlib-metadata ; python_version == "3.8"
